rsutils/__init__.py
rsutils/env.py
rsutils-0.0.2.dist-info/LICENSE
rsutils-0.0.2.dist-info/METADATA
rsutils-0.0.2.dist-info/WHEEL
rsutils-0.0.2.dist-info/top_level.txt
rsutils-0.0.2.dist-info/RECORD
